ibm_cloud_sdk_core/__init__.py
ibm_cloud_sdk_core/api_exception.py
ibm_cloud_sdk_core/base_service.py
ibm_cloud_sdk_core/detailed_response.py
ibm_cloud_sdk_core/get_authenticator.py
ibm_cloud_sdk_core/http_adapter.py
ibm_cloud_sdk_core/logger.py
ibm_cloud_sdk_core/private_helpers.py
ibm_cloud_sdk_core/utils.py
ibm_cloud_sdk_core/version.py
ibm_cloud_sdk_core/authenticators/__init__.py
ibm_cloud_sdk_core/authenticators/authenticator.py
ibm_cloud_sdk_core/authenticators/basic_authenticator.py
ibm_cloud_sdk_core/authenticators/bearer_token_authenticator.py
ibm_cloud_sdk_core/authenticators/container_authenticator.py
ibm_cloud_sdk_core/authenticators/cp4d_authenticator.py
ibm_cloud_sdk_core/authenticators/iam_assume_authenticator.py
ibm_cloud_sdk_core/authenticators/iam_authenticator.py
ibm_cloud_sdk_core/authenticators/iam_request_based_authenticator.py
ibm_cloud_sdk_core/authenticators/mcsp_authenticator.py
ibm_cloud_sdk_core/authenticators/mcspv2_authenticator.py
ibm_cloud_sdk_core/authenticators/no_auth_authenticator.py
ibm_cloud_sdk_core/authenticators/vpc_instance_authenticator.py
ibm_cloud_sdk_core/token_managers/__init__.py
ibm_cloud_sdk_core/token_managers/container_token_manager.py
ibm_cloud_sdk_core/token_managers/cp4d_token_manager.py
ibm_cloud_sdk_core/token_managers/iam_assume_token_manager.py
ibm_cloud_sdk_core/token_managers/iam_request_based_token_manager.py
ibm_cloud_sdk_core/token_managers/iam_token_manager.py
ibm_cloud_sdk_core/token_managers/jwt_token_manager.py
ibm_cloud_sdk_core/token_managers/mcsp_token_manager.py
ibm_cloud_sdk_core/token_managers/mcspv2_token_manager.py
ibm_cloud_sdk_core/token_managers/token_manager.py
ibm_cloud_sdk_core/token_managers/vpc_instance_token_manager.py
ibm_cloud_sdk_core-3.24.0.dist-info/licenses/LICENSE
ibm_cloud_sdk_core-3.24.0.dist-info/METADATA
ibm_cloud_sdk_core-3.24.0.dist-info/WHEEL
ibm_cloud_sdk_core-3.24.0.dist-info/top_level.txt
ibm_cloud_sdk_core-3.24.0.dist-info/RECORD
