Metadata-Version: 2.4
Name: ibm-cloud-sdk-core
Version: 3.24.0
Summary: Core library used by SDKs for IBM Cloud Services
Author-email: IBM <devxsdk@us.ibm.com>
Project-URL: Repository, https://github.com/IBM/python-sdk-core
Project-URL: Documentation, https://github.com/IBM/python-sdk-core/blob/main/README.md
Project-URL: Issues, https://github.com/IBM/python-sdk-core/issues
Project-URL: Changelog, https://github.com/IBM/python-sdk-core/blob/main/CHANGELOG.md
Project-URL: Contributing, https://github.com/IBM/python-sdk-core/blob/main/CONTRIBUTING.md
Project-URL: License, https://github.com/IBM/python-sdk-core/blob/main/LICENSE
Keywords: ibm,cloud,ibm cloud services
Classifier: Programming Language :: Python
Classifier: Programming Language :: Python :: 3
Classifier: Programming Language :: Python :: 3.9
Classifier: Programming Language :: Python :: 3.10
Classifier: Programming Language :: Python :: 3.11
Classifier: Programming Language :: Python :: 3.12
Classifier: Programming Language :: Python :: 3.13
Classifier: Development Status :: 5 - Production/Stable
Classifier: Environment :: Console
Classifier: Intended Audience :: Developers
Classifier: License :: OSI Approved :: Apache Software License
Classifier: Operating System :: OS Independent
Classifier: Topic :: Software Development :: Libraries
Classifier: Topic :: Software Development :: Libraries :: Python Modules
Classifier: Topic :: Software Development :: Libraries :: Application Frameworks
Requires-Python: >=3.9
License-File: LICENSE
Requires-Dist: requests<3.0.0,>=2.31.0
Requires-Dist: urllib3<3.0.0,>=2.1.0
Requires-Dist: python_dateutil<3.0.0,>=2.8.2
Requires-Dist: PyJWT<3.0.0,>=2.8.0
Provides-Extra: dev
Requires-Dist: coverage<8.0.0,>=7.3.2; extra == "dev"
Requires-Dist: pylint<4.0.0,>=3.0.0; extra == "dev"
Requires-Dist: pytest<8.0.0,>=7.4.2; extra == "dev"
Requires-Dist: pytest-cov<5.0.0,>=4.1.0; extra == "dev"
Requires-Dist: responses<1.0.0,>=0.23.3; extra == "dev"
Requires-Dist: black<25.0.0,>=24.0.0; extra == "dev"
Provides-Extra: publish
Requires-Dist: build; extra == "publish"
Requires-Dist: twine; extra == "publish"
Dynamic: license-file
